tomathml.abi3.so
libtomathml.dylib
tomathml-0.2.6.dist-info/RECORD
tomathml-0.2.6.dist-info/WHEEL
tomathml-0.2.6.dist-info/METADATA
tomathml-0.2.6.dist-info/licenses/LICENSE
