Metadata-Version: 2.1
Name: tomathml
Version: 0.2.6
Summary: A small library to convert a text description of math to content MathML.
Author-Email: Hugh Sorby <h.sorby@auckland.ac.nz>
Classifier: License :: OSI Approved :: Apache Software License
Project-URL: Homepage, https://github.com/hsorby/tomathml
Requires-Python: >=3.9
